darkzloop/__init__.py
darkzloop/__main__.py
darkzloop/cli/__init__.py
darkzloop/cli/config.py
darkzloop/cli/detection.py
darkzloop/cli/main.py
darkzloop/cli/main_old.py
darkzloop/cli/utils.py
darkzloop/core/__init__.py
darkzloop/core/agent_executor.py
darkzloop/core/context.py
darkzloop/core/critic.py
darkzloop/core/dag.py
darkzloop/core/fsm.py
darkzloop/core/locks.py
darkzloop/core/manifest.py
darkzloop/core/runtime.py
darkzloop/core/schemas.py
darkzloop/core/semantic.py
darkzloop/core/visualize.py
darkzloop/core/executors/__init__.py
darkzloop/core/executors/api.py
darkzloop/core/executors/mock.py
darkzloop/core/executors/presets.py
darkzloop/core/executors/shell.py
darkzloop-0.8.3.dist-info/METADATA
darkzloop-0.8.3.dist-info/WHEEL
darkzloop-0.8.3.dist-info/entry_points.txt
darkzloop-0.8.3.dist-info/licenses/LICENSE
darkzloop-0.8.3.dist-info/RECORD
