Metadata-Version: 2.4
Name: darkzloop
Version: 0.8.3
Summary: Reliable. Autonomous. Model-Agnostic. Turn any LLM into a disciplined software engineer.
Project-URL: Homepage, https://github.com/darkzloop/darkzloop
Project-URL: Documentation, https://darkzloop.dev/docs
Project-URL: Repository, https://github.com/darkzloop/darkzloop
Project-URL: Changelog, https://github.com/darkzloop/darkzloop/blob/main/CHANGELOG.md
Project-URL: Bug Tracker, https://github.com/darkzloop/darkzloop/issues
Author: Darkzloop Contributors
License: MIT
License-File: LICENSE
Keywords: agent,agentic,ai,anthropic,automation,claude,cli,code-generation,coding-assistant,copilot,debugging,dev-tool,finite-state-machine,fsm,golang,llm,nodejs,ollama,openai,orchestration,python,refactoring,rust,testing,typescript
Classifier: Development Status :: 4 - Beta
Classifier: Environment :: Console
Classifier: Intended Audience :: Developers
Classifier: Intended Audience :: Information Technology
Classifier: License :: OSI Approved :: MIT License
Classifier: Operating System :: MacOS
Classifier: Operating System :: OS Independent
Classifier: Operating System :: POSIX :: Linux
Classifier: Programming Language :: Python :: 3
Classifier: Programming Language :: Python :: 3 :: Only
Classifier: Programming Language :: Python :: 3.10
Classifier: Programming Language :: Python :: 3.11
Classifier: Programming Language :: Python :: 3.12
Classifier: Topic :: Scientific/Engineering :: Artificial Intelligence
Classifier: Topic :: Software Development
Classifier: Topic :: Software Development :: Build Tools
Classifier: Topic :: Software Development :: Code Generators
Classifier: Topic :: Software Development :: Quality Assurance
Classifier: Topic :: Software Development :: Testing
Classifier: Topic :: Utilities
Classifier: Typing :: Typed
Requires-Python: >=3.10
Requires-Dist: jinja2>=3.1.0
Requires-Dist: networkx>=3.0
Requires-Dist: pydantic>=2.0.0
Requires-Dist: rich>=13.0.0
Requires-Dist: typer[all]>=0.9.0
Provides-Extra: all
Requires-Dist: anthropic>=0.18.0; extra == 'all'
Requires-Dist: openai>=1.0.0; extra == 'all'
Provides-Extra: anthropic
Requires-Dist: anthropic>=0.18.0; extra == 'anthropic'
Provides-Extra: dev
Requires-Dist: black>=23.0.0; extra == 'dev'
Requires-Dist: mypy>=1.0.0; extra == 'dev'
Requires-Dist: pytest-asyncio>=0.21.0; extra == 'dev'
Requires-Dist: pytest-cov>=4.0.0; extra == 'dev'
Requires-Dist: pytest>=7.0.0; extra == 'dev'
Requires-Dist: ruff>=0.1.0; extra == 'dev'
Provides-Extra: openai
Requires-Dist: openai>=1.0.0; extra == 'openai'
